[
  {
    "name": "Disrupt Undead",
    "school": "necromancy",
    "sub_school": "",
    "source": "player's_handbook_v.3.5",
    "description": "You direct a ray of positive energy. You must make a ranged touch attack to hit, and if the ray hits an undead creature, it deals 1d6 points of damage to it. ",
    "effect": " Ray",
    "range": " Close (25 ft. + 5 ft./2 levels)",
    "components": "verbal,somatic",
    "target": "",
    "area": "",
    "duration": " Instantaneous",
    "saving_throw": " None",
    "spell_resistance": false,
    "is_30_spell": false
  }
]